[
  {
    "updatedAt": "2024-12-15T00:47:44.304Z"
  },
  {
    "updatedAt": "2024-12-15T01:04:13.224Z"
  },
  {
    "updatedAt": "2024-12-15T01:15:04.030Z",
    "work": {
      "password": null,
      "content": [],
      "work": "conversation"
    }
  },
  {
    "id": "29eb84dd-3730-4805-914e-f5a7d0cce5d1",
    "updatedAt": "2024-12-15T01:18:59.907Z",
    "work": {
      "password": "$2b$10$DGm78N3QkKKjs1ncg8eiLeSNjQu8SQQC7IFZsYQiOatN.YnGplt36",
      "content": [
        "நீ பூங்காவிற்கு சென்றிருக்கிறாயா?"
      ],
      "work": "conversation"
    }
  },
  {
    "id": "f1b187ee-2037-412b-b1d7-f81630a80cc8",
    "updatedAt": "2024-12-15T01:20:45.764Z",
    "work": {
      "password": "$2b$10$4RT2ruY4ZMctjRDnTAhzCObHThbfY7ocX8fmyVoVodNiy1jD1sVzq",
      "content": [],
      "work": "conversation"
    }
  },
  {
    "id": "d1cbce3a-1fff-441f-ab4e-e7bf1ea048d6",
    "updatedAt": "2024-12-15T19:22:57.500Z",
    "work": {
      "password": "$2b$10$3uEVANByc7jkjLA2UbZdy.K2vwBONGFl9CtdTRsqmYA35chvzgUzG",
      "content": [
        "வணக்கம்",
        "உன் பெயர் என்ன ?",
        "மணிகண்டன்",
        "நீ பூங்காவிற்கு சென்றிருக்கிறாயா?",
        "ஆம் சென்றிருக்கிறேன்",
        "பூங்காவில் விளையாட உனக்கு பிடிக்குமா ?",
        "ஆம் எனக்கு விளையாட பிடிக்கும்",
        "உனக்கு பிடித்த பூங்காவின் பெயர் என்ன ?"
      ],
      "work": "conversation"
    }
  },
  {
    "id": "0cd34392-de20-4224-b09d-e9c91a6a8b43",
    "updatedAt": "2024-12-15T20:01:40.845Z",
    "work": {
      "password": "$2b$10$MM4xr/wZrN1viT6uvAW88OSEX8CuZHyVNpwc6acDrQLJEH6Fg5w7C",
      "content": [
        "உன் பெயர் என்ன ?",
        "அனிருத்",
        "நீ பூங்காவிற்கு சென்றிருக்கிறாயா?",
        "ஆமா நான் பூங்காவிற்கு சென்றேன்",
        "பூங்காவில் விளையாட உனக்கு பிடிக்குமா ?",
        "ஆமா எனக்கு பூங்காவில் விளையாடப் பிடிக்கும்",
        "உனக்கு பிடித்த பூங்காவின் பெயர் என்ன ?",
        "எனக்குப் பிடித்த பூங்கா சென்ட்ரல் பூங்கா",
        "பூங்காவில் என்ன செய்வாய் ?",
        "பூங்காவில் நான் ஊஞ்சல் ஆடுவேன்",
        "பூங்காவில் என்ன பார்த்தாய் ?"
      ],
      "work": "conversation"
    }
  },
  {
    "id": "a0f6d0fa-0053-4199-b9ce-4395e0b35317",
    "updatedAt": "2024-12-15T20:04:19.973Z",
    "work": {
      "password": "$2b$10$1rs.zMt34rMbd/p/QC0QRebIOV4EHRbYa5wL9BdtulbT5dfiqpHIu",
      "content": [
        "வணக்கம்",
        "உன் பெயர் என்ன ?",
        "என் பெயர் அனிருத்",
        "புலியின் காலில் என்ன குத்தியது ?",
        "பொலியன் கால முல்லு குத்தியது",
        "புலி காலில் இருந்த முள்ளை  எடுக்க முயற்சி செய்ததா?",
        "ஆமாம் புளியங்காளில் இறந்தமுள்ள முயற்சி செய்தது",
        "அவர் ஏன் புலியின் காலில் இருந்த முள்ளை எடுத்தார் ?",
        "ஏன்னா தொழில் என் பாவம் பார்த்து எடுத்தது",
        "கொள்ளைக்காரர்கள் ஏன் மனிதனை புலி இருந்த கூண்டினுள் தூக்கி போட்டனர் ?",
        "ஏன்னா அவங்க அவர்கள்",
        "இந்த கதையிலிருந்து  நீ தெரிந்து கொண்டது என்ன ?",
        "நீ நல்லது செஞ்சா நல்லது திருப்பி வரும்",
        "நன்றி வணக்கம்"
      ],
      "work": "conversation"
    }
  },
  {
    "id": "b19eb3c0-0712-43e7-b6d4-95986a7baddc",
    "updatedAt": "2024-12-15T20:12:00.214Z",
    "work": {
      "password": "$2b$10$s2YcN7Do2so/UQ8VcoKIxunVeNSuFC0P/lpnMH1psi1BnEEdioNiK",
      "content": [
        "வணக்கம்",
        "உன் பெயர் என்ன ?",
        "என் பெயர் அபிஷேக்",
        "நீ பூங்காவிற்கு சென்றிருக்கிறாயா?",
        "நான் ஆம் நான் பூங்காவிற்கு சென்று இருக்கிறேன்",
        "பூங்காவில் விளையாட உனக்கு பிடிக்குமா ?",
        "எனக்கு பூங்காவிற்கு செல்வது மிகவும் பிடிக்கும்",
        "உனக்கு பிடித்த பூங்காவின் பெயர் என்ன ?",
        "எனக்கு பிடித்த பூங்காவின் பெயர் டிக்ஸன் லேண்டிங் பார்ப்போம்",
        "பூங்காவில் என்ன செய்வாய் ?",
        "பூங்காவில் நான் என் நண்பர்கள் உடன் விளையாடுவேன்",
        "பூங்காவில் என்ன பார்த்தாய் ?"
      ],
      "work": "conversation"
    }
  },
  {
    "id": "784b2a0f-8386-4757-ba83-45519776ab74",
    "updatedAt": "2024-12-15T20:14:55.349Z",
    "work": {
      "password": "$2b$10$NQSAT1ekMwkZux7543ZMVec6cP/57h0y2dJu2cfJdzlslstIQ9k3a",
      "content": [
        "வணக்கம்",
        "உன் பெயர் என்ன ?",
        "என் பெயர் அபிஷேக்",
        "புலியின் காலில் என்ன குத்தியது ?",
        "புலியின் காலில் ஒரு முள் குத்தியது",
        "புலி காலில் இருந்த முள்ளை  எடுக்க முயற்சி செய்ததா?",
        "புலியின் காலில் இருந்த முள்ளே எடுக்க புலி முயற்சி செய்தது ஆனால் அதால் எடுக்க முடியவில்லை",
        "அவர் ஏன் புலியின் காலில் இருந்த முள்ளை எடுத்தார் ?",
        "அவர் புள்ளியின் காலில் உள்ள முல்லை ஏன் எடுத்தார் என்றால் அவரை அவர் புலியை பார்த்து மிகவும் வருத்தமாக இருந்தார்",
        "கொள்ளைக்காரர்கள் ஏன் மனிதனை புலி இருந்த கூண்டினுள் தூக்கி போட்டனர் ?",
        "கொள்ளைக்காரர்கள் அந்த புலி ஒரு மனிதனை ஃபைட் என்னது சண்டே போட பார்க்க வேண்டும் என்று நினைத்தார்கள்",
        "இந்த கதையிலிருந்து  நீ தெரிந்து கொண்டது என்ன ?",
        "நான் இந்த கடையிலிருந்து நன்று செய்தால் நன்று உனக்கும் கிடைக்கும் என்று கற்றுக் கொண்டேன்",
        "நன்றி வணக்கம்"
      ],
      "work": "conversation"
    }
  },
  {
    "id": "5847c1f2-7feb-4770-8657-5742a0a4cb4e",
    "updatedAt": "2024-12-15T20:21:42.705Z",
    "work": {
      "password": "$2b$10$7q2uyPLKpjCRv.vBXMNxreWWpCDf3xaGkr7swUGEWF/WCokQJdho.",
      "content": [
        "வணக்கம்",
        "உன் பெயர் என்ன ?",
        "என் பெயர் சிஜின்",
        "நீ பூங்காவிற்கு சென்றிருக்கிறாயா?",
        "நான் பூங்காவுக்கு சென்றிருக்கிறேன்",
        "பூங்காவில் விளையாட உனக்கு பிடிக்குமா ?",
        "ஆமா எனக்கு பூங்காவில் விளையாட பிடிக்கும்",
        "உனக்கு பிடித்த பூங்காவின் பெயர் என்ன ?",
        "எனக்கு பிடித்த பூங்காவோட பெயர் இவரின் டன் பூங்கா",
        "பூங்காவில் என்ன செய்வாய் ?",
        "பூங்காவ நான் கைப்பந்து விளையாடுவேன்",
        "பூங்காவில் என்ன பார்த்தாய் ?"
      ],
      "work": "conversation"
    }
  }
]